odoo/addons/account_payment_show_invoice/README.rst
odoo/addons/account_payment_show_invoice/__init__.py
odoo/addons/account_payment_show_invoice/__manifest__.py
odoo/addons/account_payment_show_invoice/i18n/account_payment_show_invoice.pot
odoo/addons/account_payment_show_invoice/i18n/it.po
odoo/addons/account_payment_show_invoice/readme/CONTRIBUTORS.md
odoo/addons/account_payment_show_invoice/readme/DESCRIPTION.md
odoo/addons/account_payment_show_invoice/readme/USAGE.md
odoo/addons/account_payment_show_invoice/static/description/icon.png
odoo/addons/account_payment_show_invoice/static/description/index.html
odoo/addons/account_payment_show_invoice/views/account_payment_view.xml
odoo_addon_account_payment_show_invoice-18.0.1.0.0.3.dist-info/METADATA
odoo_addon_account_payment_show_invoice-18.0.1.0.0.3.dist-info/WHEEL
odoo_addon_account_payment_show_invoice-18.0.1.0.0.3.dist-info/top_level.txt
odoo_addon_account_payment_show_invoice-18.0.1.0.0.3.dist-info/RECORD
