Metadata-Version: 2.1
Name: odoo-addon-account_payment_show_invoice
Version: 18.0.1.0.0.3
Requires-Python: >=3.10
Requires-Dist: odoo==18.0.*
Summary: Extends the tree view of payments to show the paid invoices related to the payments using the vendor reference by default
Home-page: https://github.com/OCA/account-payment
License: AGPL-3
Author: ForgeFlow, Odoo Community Association (OCA)
Author-email: support@odoo-community.org
Classifier: Programming Language :: Python
Classifier: Framework :: Odoo
Classifier: Framework :: Odoo :: 18.0
Classifier: License :: OSI Approved :: GNU Affero General Public License v3
